freethinkdb/__init__.py
freethinkdb/__main__.py
freethinkdb/_dump.py
freethinkdb/_export.py
freethinkdb/_import.py
freethinkdb/_index_rebuild.py
freethinkdb/_restore.py
freethinkdb/ast.py
freethinkdb/docs.py
freethinkdb/errors.py
freethinkdb/handshake.py
freethinkdb/net.py
freethinkdb/query.py
freethinkdb/utils_common.py
freethinkdb/version.py
freethinkdb/backports/__init__.py
freethinkdb/backports/ssl_match_hostname/LICENSE.txt
freethinkdb/backports/ssl_match_hostname/README.txt
freethinkdb/backports/ssl_match_hostname/__init__.py
freethinkdb/gevent_net/__init__.py
freethinkdb/gevent_net/net_gevent.py
freethinkdb/tornado_net/__init__.py
freethinkdb/tornado_net/net_tornado.py
freethinkdb/twisted_net/__init__.py
freethinkdb/twisted_net/net_twisted.py
freethinkdb-2.3.0.post3.dist-info/DESCRIPTION.rst
freethinkdb-2.3.0.post3.dist-info/METADATA
freethinkdb-2.3.0.post3.dist-info/RECORD
freethinkdb-2.3.0.post3.dist-info/WHEEL
freethinkdb-2.3.0.post3.dist-info/entry_points.txt
freethinkdb-2.3.0.post3.dist-info/metadata.json
freethinkdb-2.3.0.post3.dist-info/top_level.txt
freethinkdb-2.3.0.post3.dist-info/zip-safe
