Metadata-Version: 2.0
Name: freethinkdb
Version: 2.3.0.post3
Summary: Python driver library for the FreethinkDB database server.
Home-page: http://freethinkdb.org
Author: FreethinkDB
Author-email: ross+freethinkdb@kukulinski.com
License: UNKNOWN
Platform: UNKNOWN
